README.rst
setup.cfg
setup.py
faaspot/__init__.py
faaspot/faaspot.py
fas/VERSION
fas/__init__.py
fas/config.py
fas/main.py
fas/table.py
fas/utils.py
fas.egg-info/PKG-INFO
fas.egg-info/SOURCES.txt
fas.egg-info/dependency_links.txt
fas.egg-info/entry_points.txt
fas.egg-info/requires.txt
fas.egg-info/top_level.txt
fas/cli/__init__.py
fas/cli/arguments.py
fas/cli/executions.py
fas/cli/functions.py
fas/cli/nodes.py
fas/cli/profiles.py
fas/client/__init__.py
fas/client/exceptions.py
fas/client/httpclient.py
fas/commands/__init__.py
fas/commands/command.py
fas/commands/executions.py
fas/commands/functions.py
fas/commands/nodes.py
fas/commands/profiles.py
fas/commands/samples/get-content.py
fas/commands/samples/hello-world.py
fas/commands/samples/sleep.py